{
  "${ModID}:Example": {
    "NAME": "",
    "DESCRIPTION": "",
    "UPGRADE_DESCRIPTION": "",
    "EXTENDED_DESCRIPTION": [""]
  },
  "${ModID}:Battery": {
    "NAME": "Battery",
    "DESCRIPTION": "Gain [E] ."
  },
  "${ModID}:BrassPlating": {
    "NAME": "Brass Plating",
    "DESCRIPTION": "+ !M! Block."
  },
  "${ModID}:BrokenSprockets": {
    "NAME": "Broken Sprockets",
    "DESCRIPTION": "+ !M! damage."
  },
  "${ModID}:CoolantValve": {
    "NAME": "",
    "DESCRIPTION": ""
  },
  "${ModID}:CryonicCrystal": {
    "NAME": "",
    "DESCRIPTION": ""
  },
  "${ModID}:EmberForge": {
    "NAME": "Ember Forge",
    "DESCRIPTION": "Reduce cost to 0."
  },
  "${ModID}:GlowingMetal": {
    "NAME": "Glowing Metal",
    "DESCRIPTION": "Apples 3 snowpunk:Burn on hit."
  },
  "${ModID}:Gyroscopter": {
    "NAME": "Gyroscopter",
    "DESCRIPTION": "snowpunk:Reshuffle."
  },
  "${ModID}:HeatingCoils": {
    "NAME": "",
    "DESCRIPTION": ""
  },
  "${ModID}:ManastoneCasing": {
    "NAME": "Manastone Casing",
    "DESCRIPTION": "+ 2 snowpunk:Primary."
  },
  "${ModID}:OiledGears": {
    "NAME": "Oiled Gears",
    "DESCRIPTION": "Draw 1 card."
  },
  "${ModID}:ScrapHeap": {
    "NAME": "",
    "DESCRIPTION": ""
  },
  "${ModID}:SpareSpikes": {
    "NAME": "",
    "DESCRIPTION": ""
  },






  "${ModID}:BarrierCore": {
    "NAME": "Barrier Core",
    "DESCRIPTION": "Gain !B! Block.",
    "EXTENDED_DESCRIPTION": ["Barrier","Gain %s Block."]
  },
  "${ModID}:BismuthCore": {
    "NAME": "Bismuth Core",
    "DESCRIPTION": "Apply a debuff",
    "EXTENDED_DESCRIPTION": ["Basher","Apply !M! Vulnerable.","Sweeper","Apply !M! Weak.","Blackener","Apply !M! snowpunk:Soot.","Shackler","Enemy loses !M! Strength this turn."]
  },
  "${ModID}:AbyssalCore": {
    "NAME": "Abyssal Core",
    "DESCRIPTION": "Apply a debuff",
    "EXTENDED_DESCRIPTION": ["Tripper","Apply !M! Vulnerable to ALL enemies.","Blinder","Apply !M! Weak to ALL enemies.","Duster","Apply !M! snowpunk:Soot to ALL enemies.","Piercer","ALL enemies lose !M! Strength this turn."]
  },
  "${ModID}:BlastCore": {
    "NAME": "Blast Core",
    "DESCRIPTION": "Deal !D! damage to ALL enemies.",
    "EXTENDED_DESCRIPTION": ["Blaster","Deal %s damage to ALL enemies."]
  },
  "${ModID}:StrikeCore": {
    "NAME": "Strike Core",
    "DESCRIPTION": "Deal !D! damage.",
    "EXTENDED_DESCRIPTION": ["Striker","Deal %s damage."]
  },
  "${ModID}:CombustionCore": {
    "NAME": "Combustion Core",
    "DESCRIPTION": "Powerful damage effect",
    "EXTENDED_DESCRIPTION": ["Eviscerater","Deal !D! damage 3 times.","Killer","Deal !D! damage to ALL enemies.","Hammer","Deal !D! damage.","Ripper","Deal !D! damage twice."]
  }
}